mozzarilla/AUTHORS.TXT
mozzarilla/CHANGELOG.MD
mozzarilla/LICENSE
mozzarilla/README.MD
mozzarilla/__init__.py
mozzarilla/__main__.py
mozzarilla/app_window.py
mozzarilla/editor_constants.py
mozzarilla/mozzarilla.ico
mozzarilla/mozzarilla.png
mozzarilla/msg.dat
mozzarilla/run.py
mozzarilla/defs/__init__.py
mozzarilla/defs/config_def.py
mozzarilla/defs/guerilla_workspace_def.py
mozzarilla/defs/upgrade_config.py
mozzarilla/defs/v2_config_def.py
mozzarilla/styles/dark red.sty
mozzarilla/styles/guerilla.sty
mozzarilla/styles/light.sty
mozzarilla/widgets/__init__.py
mozzarilla/widgets/directory_frame.py
mozzarilla/widgets/field_widget_picker.py
mozzarilla/widgets/field_widgets/__init__.py
mozzarilla/widgets/field_widgets/computed_text_frames.py
mozzarilla/widgets/field_widgets/dependency_frame.py
mozzarilla/widgets/field_widgets/dynamic_enum_frame.py
mozzarilla/widgets/field_widgets/font_display_frame.py
mozzarilla/widgets/field_widgets/halo_1_bitmap_display.py
mozzarilla/widgets/field_widgets/halo_2_bitmap_display.py
mozzarilla/widgets/field_widgets/halo_3_bitmap_display.py
mozzarilla/widgets/field_widgets/halo_color_picker_frame.py
mozzarilla/widgets/field_widgets/meter_display_frame.py
mozzarilla/widgets/field_widgets/rawdata_frames.py
mozzarilla/widgets/field_widgets/reflexive_frame.py
mozzarilla/windows/__init__.py
mozzarilla/windows/tag_window.py
mozzarilla/windows/tag_converters/__init__.py
mozzarilla/windows/tag_converters/chicago_shader_converter.py
mozzarilla/windows/tag_converters/collision_converter.py
mozzarilla/windows/tag_converters/converter_base.py
mozzarilla/windows/tag_converters/gbxmodel_converter.py
mozzarilla/windows/tag_converters/model_animations_converter.py
mozzarilla/windows/tag_converters/model_converter.py
mozzarilla/windows/tag_converters/object_converter.py
mozzarilla/windows/tag_converters/sbsp_converter.py
mozzarilla/windows/tools/__init__.py
mozzarilla/windows/tools/animations_compiler_window.py
mozzarilla-1.10.0.dist-info/AUTHORS.TXT
mozzarilla-1.10.0.dist-info/LICENSE
mozzarilla-1.10.0.dist-info/METADATA
mozzarilla-1.10.0.dist-info/WHEEL
mozzarilla-1.10.0.dist-info/top_level.txt
mozzarilla-1.10.0.dist-info/RECORD
