Metadata-Version: 2.1
Name: mozzarilla
Version: 1.10.0
Summary: A variant of Binilla for editing binary structures for games built with the Blam engine.
Home-page: https://github.com/Sigmmma/mozzarilla
Author: Sigmmma
Author-email: MoeMakesStuff@gmail.com
License: GPLv3
Project-URL: Source, https://github.com/Sigmmma/mozzarilla
Project-URL: Funding, https://liberapay.com/MEK/
Keywords: binilla,binary,data structure
Platform: POSIX
Platform: Windows
Classifier: Development Status :: 4 - Beta
Classifier: Intended Audience :: End Users/Desktop
Classifier: License :: OSI Approved :: GNU General Public License v3 (GPLv3)
Classifier: Programming Language :: Python
Classifier: Programming Language :: Python :: 3
Classifier: Programming Language :: Python :: 3.5
Classifier: Programming Language :: Python :: 3.6
Classifier: Programming Language :: Python :: 3.7
Classifier: Programming Language :: Python :: 3.8
Classifier: Programming Language :: Python :: 3.9
Classifier: Programming Language :: Python :: 3 :: Only
Requires: reclaimer
Requires: arbytmap
Requires: binilla
Provides: mozzarilla
Requires-Python: >=3.5
Requires-Dist: reclaimer
Requires-Dist: binilla
Requires-Dist: arbytmap
Requires-Dist: supyr-struct
